command_tool.py
configuration.py
lzo.py
mdict_dir.py
mdict_query.py
pure_salsa20.py
readmdict.py
ripemd128.py
setup.py
anki/__init__.py
anki/data_query.py
anki/data/__init__.py
anki/data/baicizhan_service.py
anki/data/cobuild_service.py
anki/data/data_service.py
anki/data/dict_service.py
anki/data/macmillan_service.py
anki/service/__init__.py
anki/service/baicizhan.py
anki/service/base.py
anki_tool.egg-info/PKG-INFO
anki_tool.egg-info/SOURCES.txt
anki_tool.egg-info/dependency_links.txt
anki_tool.egg-info/entry_points.txt
anki_tool.egg-info/not-zip-safe
anki_tool.egg-info/requires.txt
anki_tool.egg-info/top_level.txt