Metadata-Version: 1.1
Name: anki-tool
Version: 1.0.6
Summary: A anki word query tool
Home-page: https://github.com/momodae
Author: jack chen
Author-email: lazilylamp@gmail.com
License: UNKNOWN
Platform: UNKNOWN
Classifier: Programming Language :: Python :: 3.5
